notebook_2_py/__init__.py
notebook_2_py/notebook_2_py.py
notebook_2_py-0.0.14.dist-info/LICENSE
notebook_2_py-0.0.14.dist-info/METADATA
notebook_2_py-0.0.14.dist-info/WHEEL
notebook_2_py-0.0.14.dist-info/top_level.txt
notebook_2_py-0.0.14.dist-info/RECORD
